pyOpenRPA/Info.md
pyOpenRPA/LICENSE.pdf
pyOpenRPA/README.md
pyOpenRPA/__init__.py
pyOpenRPA/Agent/A2O.py
pyOpenRPA/Agent/O2A.py
pyOpenRPA/Agent/Processor.py
pyOpenRPA/Agent/__Agent__.py
pyOpenRPA/Agent/__init__.py
pyOpenRPA/Agent/readme.md
pyOpenRPA/Orchestrator/BackwardCompatibility.py
pyOpenRPA/Orchestrator/ControlPanel.py
pyOpenRPA/Orchestrator/Core.py
pyOpenRPA/Orchestrator/Processor.py
pyOpenRPA/Orchestrator/ProcessorOld.py
pyOpenRPA/Orchestrator/Server.py
pyOpenRPA/Orchestrator/ServerBC.py
pyOpenRPA/Orchestrator/ServerSettings.py
pyOpenRPA/Orchestrator/SettingsTemplate.py
pyOpenRPA/Orchestrator/Timer.py
pyOpenRPA/Orchestrator/__Orchestrator__.py
pyOpenRPA/Orchestrator/__init__.py
pyOpenRPA/Orchestrator/__main__.py
pyOpenRPA/Orchestrator/Managers/ControlPanel.py
pyOpenRPA/Orchestrator/Managers/Git.py
pyOpenRPA/Orchestrator/Managers/Process.py
pyOpenRPA/Orchestrator/Managers/__init__.py
pyOpenRPA/Orchestrator/RobotRDPActive/CMDStr.py
pyOpenRPA/Orchestrator/RobotRDPActive/Clipboard.py
pyOpenRPA/Orchestrator/RobotRDPActive/Connector.py
pyOpenRPA/Orchestrator/RobotRDPActive/ConnectorExceptions.py
pyOpenRPA/Orchestrator/RobotRDPActive/Processor.py
pyOpenRPA/Orchestrator/RobotRDPActive/Recovery.py
pyOpenRPA/Orchestrator/RobotRDPActive/RobotRDPActive.py
pyOpenRPA/Orchestrator/RobotRDPActive/Scheduler.py
pyOpenRPA/Orchestrator/RobotRDPActive/Template.rdp
pyOpenRPA/Orchestrator/RobotRDPActive/Timer.py
pyOpenRPA/Orchestrator/RobotRDPActive/__init__.py
pyOpenRPA/Orchestrator/RobotRDPActive/__main__.py
pyOpenRPA/Orchestrator/RobotScreenActive/ConsoleStart.bat
pyOpenRPA/Orchestrator/RobotScreenActive/Monitor.py
pyOpenRPA/Orchestrator/RobotScreenActive/Screen.py
pyOpenRPA/Orchestrator/RobotScreenActive/__init__.py
pyOpenRPA/Orchestrator/RobotScreenActive/__main__.py
pyOpenRPA/Orchestrator/Utils/LoggerHandlerDumpLogList.py
pyOpenRPA/Orchestrator/Utils/__init__.py
pyOpenRPA/Orchestrator/Web/Basic.py
pyOpenRPA/Resources/Web/Google/LatoItalic.css
orpa-0.0.0.dist-info/METADATA
orpa-0.0.0.dist-info/WHEEL
orpa-0.0.0.dist-info/top_level.txt
orpa-0.0.0.dist-info/RECORD
