Metadata-Version: 2.1
Name: orpa
Version: 0.0.0
Summary: The powerful open source RPA platform for business (pyOpenRPA)
Home-page: https://orpa.app/
Author: Ivan Maslov
Author-email: Ivan.Maslov@pyopenrpa.ru
License: Текст лицензии см. в файле по адресу: https://pyopenrpa.ru/license/oferta.pdf
Keywords: ORPA pyOpenRPA OpenRPA RPA Robot Automation Robotization OpenSource
Platform: UNKNOWN
Classifier: Development Status :: 5 - Production/Stable
Classifier: License :: Free For Educational Use
Classifier: License :: Free For Home Use
Classifier: License :: Free for non-commercial use
Classifier: Intended Audience :: Developers
Classifier: Environment :: Win32 (MS Windows)
Classifier: Environment :: X11 Applications
Classifier: Programming Language :: Python
Classifier: Programming Language :: Python :: 3.7
Classifier: Programming Language :: Python :: 3.8
Classifier: Programming Language :: Python :: 3.9
Classifier: Programming Language :: Python :: 3.10
Classifier: Topic :: Software Development :: Libraries :: Python Modules
Classifier: Topic :: Software Development :: Testing
Classifier: Topic :: Software Development :: User Interfaces
Classifier: Topic :: Software Development :: Quality Assurance
Classifier: Topic :: Home Automation
Requires-Dist: pillow (>=6.0.0)
Requires-Dist: keyboard (>=0.13.3)
Requires-Dist: pyscreeze (==0.1.21)
Requires-Dist: pyautogui (<=0.9.52)
Requires-Dist: psutil (>=5.6.2)
Requires-Dist: crypto (>=1.4.1)
Requires-Dist: schedule (>=1.1.0)
Requires-Dist: Jinja2 (>=2.2.11.2)
Requires-Dist: selenium (==3.141.0)
Requires-Dist: fastapi (>=0.81.0)
Requires-Dist: uvicorn (>=0.18.3)
Requires-Dist: python-multipart (>=0.0.6)
Requires-Dist: autodocsumm (>=0.2.10)
Requires-Dist: screeninfo (>=0.8.1)
Requires-Dist: pytesseract
Requires-Dist: simplepam (>=0.1.5) ; "linux" in sys_platform
Requires-Dist: pyclip (>=0.6.0) ; "linux" in sys_platform
Requires-Dist: pywin32 (>=224) ; sys_platform == "win32"
Requires-Dist: WMI (>=1.4.9) ; sys_platform == "win32"
Requires-Dist: pywinauto (>=0.6.8) ; sys_platform == "win32"
Requires-Dist: desktopmagic ; sys_platform == "win32"
